setup.py
my_one/Binomialdistribution.py
my_one/Gaussiandistribution.py
my_one/Generaldistribution.py
my_one/__init__.py
my_one.egg-info/PKG-INFO
my_one.egg-info/SOURCES.txt
my_one.egg-info/dependency_links.txt
my_one.egg-info/not-zip-safe
my_one.egg-info/top_level.txt